decoraid/__init__.py
decoraid/cli.py
decoraid/cpdec.py
decoraid/trace.py
decoraid-0.0.21.dist-info/LICENSE
decoraid-0.0.21.dist-info/METADATA
decoraid-0.0.21.dist-info/WHEEL
decoraid-0.0.21.dist-info/entry_points.txt
decoraid-0.0.21.dist-info/RECORD
