Metadata-Version: 2.3
Name: decoraid
Version: 0.0.21
Summary: A set of usefull Python decorator's. 
License: MIT
Author: ankit k
Author-email: ankit48365@gmail.com
Requires-Python: >=3.9,<4.0
Classifier: License :: OSI Approved :: MIT License
Classifier: Programming Language :: Python :: 3
Classifier: Programming Language :: Python :: 3.9
Classifier: Programming Language :: Python :: 3.10
Classifier: Programming Language :: Python :: 3.11
Classifier: Programming Language :: Python :: 3.12
Classifier: Programming Language :: Python :: 3.13
Project-URL: Repository, https://github.com/ankit48365/decoraid
